{
  "address": "io10p7eerqjmzdha5ven0x3g7zlxt95cy3ftzq43r",
  "name": "IOTEXCHART",
  "description": null,
  "logo": null,
  "symbol": "IOTEXCHART",
  "decimals": 9,
  "total_supply": "1000000000000000000",
  "transfer": "2",
  "daily_transfer": "0",
  "daily_transfer_amount": null,
  "holders": 3,
  "id": 1990,
  "custom_config": {},
  "social_media": {},
  "is_depin_token": false,
  "is_official": false,
  "daily_volume_usd": null,
  "total_liquidity_usd": null,
  "coingecko_id": null,
  "markets": [],
  "updated_at": "2024-07-02T08:30:07.878Z"
}