{
  "address": "io127ygd8gfkf8qvquy3tyj7dk00dgfyfugpyyhyh",
  "name": "PBG",
  "description": null,
  "logo": null,
  "symbol": "PBG",
  "decimals": 18,
  "total_supply": "100000000000000000000000000",
  "transfer": "1",
  "daily_transfer": "0",
  "daily_transfer_amount": null,
  "holders": 2,
  "id": 2063,
  "custom_config": {},
  "social_media": {},
  "is_depin_token": false,
  "is_official": false,
  "daily_volume_usd": null,
  "total_liquidity_usd": null,
  "coingecko_id": null,
  "markets": [],
  "updated_at": "2024-07-02T08:30:07.878Z"
}